<annotation>
	<folder>Grape_Black_rot</folder>
	<filename>017268b1-c25c-4299-a566-1b7ba3f1591e___FAM_B.Rot 3014.JPG</filename>
	<path>D:\GoogleDownload\GrapeDeseaseDataset\Grape_Black_rot\017268b1-c25c-4299-a566-1b7ba3f1591e___FAM_B.Rot 3014.JPG</path>
	<source>
		<database>Unknown</database>
	</source>
	<size>
		<width>256</width>
		<height>256</height>
		<depth>3</depth>
	</size>
	<segmented>0</segmented>
	<object>
		<name>black_rot</name>
		<pose>Unspecified</pose>
		<truncated>0</truncated>
		<difficult>0</difficult>
		<bndbox>
			<xmin>126</xmin>
			<ymin>137</ymin>
			<xmax>141</xmax>
			<ymax>149</ymax>
		</bndbox>
	</object>
	<object>
		<name>black_rot</name>
		<pose>Unspecified</pose>
		<truncated>0</truncated>
		<difficult>0</difficult>
		<bndbox>
			<xmin>178</xmin>
			<ymin>159</ymin>
			<xmax>190</xmax>
			<ymax>173</ymax>
		</bndbox>
	</object>
	<object>
		<name>black_rot</name>
		<pose>Unspecified</pose>
		<truncated>0</truncated>
		<difficult>0</difficult>
		<bndbox>
			<xmin>97</xmin>
			<ymin>65</ymin>
			<xmax>111</xmax>
			<ymax>80</ymax>
		</bndbox>
	</object>
	<object>
		<name>black_rot</name>
		<pose>Unspecified</pose>
		<truncated>0</truncated>
		<difficult>0</difficult>
		<bndbox>
			<xmin>38</xmin>
			<ymin>105</ymin>
			<xmax>58</xmax>
			<ymax>129</ymax>
		</bndbox>
	</object>
	<object>
		<name>black_rot</name>
		<pose>Unspecified</pose>
		<truncated>0</truncated>
		<difficult>0</difficult>
		<bndbox>
			<xmin>50</xmin>
			<ymin>73</ymin>
			<xmax>62</xmax>
			<ymax>83</ymax>
		</bndbox>
	</object>
</annotation>
