<annotation>
	<folder>Grape_Esca_(Black_Measles)</folder>
	<filename>black_measles	(227).JPG</filename>
	<path>D:\GoogleDownload\GrapeDeseaseDataset\Grape_Esca_(Black_Measles)\black_measles	(227).JPG</path>
	<source>
		<database>Unknown</database>
	</source>
	<size>
		<width>256</width>
		<height>256</height>
		<depth>3</depth>
	</size>
	<segmented>0</segmented>
	<object>
		<name>black_measles</name>
		<pose>Unspecified</pose>
		<truncated>0</truncated>
		<difficult>0</difficult>
		<bndbox>
			<xmin>31</xmin>
			<ymin>130</ymin>
			<xmax>57</xmax>
			<ymax>150</ymax>
		</bndbox>
	</object>
	<object>
		<name>black_measles</name>
		<pose>Unspecified</pose>
		<truncated>0</truncated>
		<difficult>0</difficult>
		<bndbox>
			<xmin>41</xmin>
			<ymin>102</ymin>
			<xmax>65</xmax>
			<ymax>125</ymax>
		</bndbox>
	</object>
	<object>
		<name>black_measles</name>
		<pose>Unspecified</pose>
		<truncated>0</truncated>
		<difficult>0</difficult>
		<bndbox>
			<xmin>69</xmin>
			<ymin>81</ymin>
			<xmax>83</xmax>
			<ymax>94</ymax>
		</bndbox>
	</object>
	<object>
		<name>black_measles</name>
		<pose>Unspecified</pose>
		<truncated>0</truncated>
		<difficult>0</difficult>
		<bndbox>
			<xmin>48</xmin>
			<ymin>91</ymin>
			<xmax>63</xmax>
			<ymax>101</ymax>
		</bndbox>
	</object>
	<object>
		<name>black_measles</name>
		<pose>Unspecified</pose>
		<truncated>0</truncated>
		<difficult>0</difficult>
		<bndbox>
			<xmin>107</xmin>
			<ymin>43</ymin>
			<xmax>118</xmax>
			<ymax>58</ymax>
		</bndbox>
	</object>
</annotation>
