<annotation>
	<folder>Grape_Black_rot</folder>
	<filename>c594f0a4-cfb5-4d84-b216-64b0dcf272c2___FAM_B.Rot 3464.JPG</filename>
	<path>D:\GoogleDownload\GrapeDeseaseDataset\Grape_Black_rot\c594f0a4-cfb5-4d84-b216-64b0dcf272c2___FAM_B.Rot 3464.JPG</path>
	<source>
		<database>Unknown</database>
	</source>
	<size>
		<width>256</width>
		<height>256</height>
		<depth>3</depth>
	</size>
	<segmented>0</segmented>
	<object>
		<name>black_rot</name>
		<pose>Unspecified</pose>
		<truncated>0</truncated>
		<difficult>0</difficult>
		<bndbox>
			<xmin>159</xmin>
			<ymin>165</ymin>
			<xmax>182</xmax>
			<ymax>185</ymax>
		</bndbox>
	</object>
	<object>
		<name>black_rot</name>
		<pose>Unspecified</pose>
		<truncated>0</truncated>
		<difficult>0</difficult>
		<bndbox>
			<xmin>85</xmin>
			<ymin>107</ymin>
			<xmax>102</xmax>
			<ymax>122</ymax>
		</bndbox>
	</object>
</annotation>
