<annotation>
	<folder>Grape_Black_rot</folder>
	<filename>d14d8e05-c7f8-45cc-a733-9b76aba7300d___FAM_B.Rot 3629.JPG</filename>
	<path>D:\GoogleDownload\GrapeDeseaseDataset\Grape_Black_rot\d14d8e05-c7f8-45cc-a733-9b76aba7300d___FAM_B.Rot 3629.JPG</path>
	<source>
		<database>Unknown</database>
	</source>
	<size>
		<width>256</width>
		<height>256</height>
		<depth>3</depth>
	</size>
	<segmented>0</segmented>
	<object>
		<name>black_rot</name>
		<pose>Unspecified</pose>
		<truncated>0</truncated>
		<difficult>0</difficult>
		<bndbox>
			<xmin>106</xmin>
			<ymin>151</ymin>
			<xmax>130</xmax>
			<ymax>178</ymax>
		</bndbox>
	</object>
	<object>
		<name>black_rot</name>
		<pose>Unspecified</pose>
		<truncated>0</truncated>
		<difficult>0</difficult>
		<bndbox>
			<xmin>123</xmin>
			<ymin>93</ymin>
			<xmax>158</xmax>
			<ymax>129</ymax>
		</bndbox>
	</object>
	<object>
		<name>black_rot</name>
		<pose>Unspecified</pose>
		<truncated>0</truncated>
		<difficult>0</difficult>
		<bndbox>
			<xmin>159</xmin>
			<ymin>78</ymin>
			<xmax>212</xmax>
			<ymax>124</ymax>
		</bndbox>
	</object>
	<object>
		<name>black_rot</name>
		<pose>Unspecified</pose>
		<truncated>0</truncated>
		<difficult>0</difficult>
		<bndbox>
			<xmin>107</xmin>
			<ymin>205</ymin>
			<xmax>129</xmax>
			<ymax>220</ymax>
		</bndbox>
	</object>
</annotation>
